task3/f1sequence.sv
module f1sequence(
    input logic clk,
    input logic rst,
    input logic in,
    output logic [7:0] out
);

    typedef enum {S0,S1,S2,S3,S4,S5,S6,S7,S8  } f1sequence;
    f1sequence current_state, next_state;

    always_ff @(posedge clk) 
        if(rst)     current_state <= S0;
        else        current_state <= next_state;    
    

    always_comb 
        case (current_state)
            S0: if (in == 1'b1) next_state = S1;
            S1: if (in == 1'b1) next_state = S2;
            S2: if (in == 1'b1) next_state = S3;
            S3: if (in == 1'b1) next_state = S4;
            S4: if (in == 1'b1) next_state = S5;
            S5: if (in == 1'b1) next_state = S6;
            S6: if (in == 1'b1) next_state = S7;
            S7: if (in == 1'b1) next_state = S8;
            S8: if (in == 1'b1) next_state = S0;

        endcase
    always_comb
        case (current_state)
            S0: out = 8'b0;
            S1: out = 8'b1;
            S2: out = 8'b1;
            S3: out = 8'b111;
            S4: out = 8'b1111;
            S5: out = 8'b11111;
            S6: out = 8'b111111;
            S7: out = 8'b1111111;
            S8: out = 8'b11111111;
            default: out = 8'b0;
        endcase
    
endmodule

task2/f1sequence.vcd
$version Generated by VerilatedVcd $end
$date Thu Nov  2 11:40:34 2023 $end
$timescale 1ps $end

 $scope module TOP $end
  $var wire  1 # clk $end
  $var wire  1 % in $end
  $var wire  8 & out [7:0] $end
  $var wire  1 $ rst $end
  $scope module f1sequence $end
   $var wire  1 # clk $end
   $var wire 32 ' current_state [31:0] $end
   $var wire  1 % in $end
   $var wire 32 ( next_state [31:0] $end
   $var wire  8 & out [7:0] $end
   $var wire  1 $ rst $end
  $upscope $end
 $upscope $end
$enddefinitions $end


#0
1#
1$
0%
b00000000 &
b00000000000000000000000000000000 '
b00000000000000000000000000000000 (
#1
0#
#2
1#
#3
0#
#4
1#
0$
#5
0#
#6
1#
#7
0#
#8
1#
#9
0#
#10
1#
#11
0#
#12
1#
#13
0#
#14
1#
#15
0#
#16
1#
#17
0#
#18
1#
#19
0#
#20
1#
#21
0#
#22
1#
#23
0#
#24
1#
#25
0#
#26
1#
#27
0#
#28
1#
#29
0#
#30
1#
#31
0#
#32
1#
#33
0#
#34
1#
#35
0#
#36
1#
#37
0#
#38
1#
#39
0#
#40
1#
#41
0#
#42
1#
#43
0#
#44
1#
#45
0#
#46
1#
#47
0#
#48
1#
#49
0#
#50
1#
#51
0#
#52
1#
#53
0#
#54
1#
#55
0#
#56
1#
#57
0#
#58
1#
#59
0#
#60
1#
#61
0#
#62
1#
#63
0#
#64
1#
#65
0#
#66
1#
#67
0#
#68
1#
#69
0#
#70
1#
1%
#71
0#
b00000000000000000000000000000001 (
#72
1#
0%
b00000001 &
b00000000000000000000000000000001 '
b00000000000000000000000000000010 (
#73
0#
#74
1#
b00000000000000000000000000000010 '
#75
0#
#76
1#
#77
0#
#78
1#
#79
0#
#80
1#
#81
0#
#82
1#
#83
0#
#84
1#
#85
0#
#86
1#
#87
0#
#88
1#
#89
0#
#90
1#
#91
0#
#92
1#
#93
0#
#94
1#
#95
0#
#96
1#
#97
0#
#98
1#
#99
0#
#100
1#
#101
0#
#102
1#
#103
0#
#104
1#
#105
0#
#106
1#
1%
#107
0#
b00000000000000000000000000000011 (
#108
1#
0%
b00000111 &
b00000000000000000000000000000011 '
b00000000000000000000000000000100 (
#109
0#
#110
1#
b00001111 &
b00000000000000000000000000000100 '
#111
0#
#112
1#
#113
0#
#114
1#
#115
0#
#116
1#
#117
0#
#118
1#
#119
0#
#120
1#
#121
0#
#122
1#
#123
0#
#124
1#
#125
0#
#126
1#
#127
0#
#128
1#
#129
0#
#130
1#
#131
0#
#132
1#
1%
#133
0#
b00000000000000000000000000000101 (
#134
1#
0%
b00011111 &
b00000000000000000000000000000101 '
b00000000000000000000000000000110 (
#135
0#
#136
1#
b00111111 &
b00000000000000000000000000000110 '
